jaraco/itertools.py
jaraco_itertools-6.4.2.dist-info/licenses/LICENSE
jaraco_itertools-6.4.2.dist-info/METADATA
jaraco_itertools-6.4.2.dist-info/WHEEL
jaraco_itertools-6.4.2.dist-info/top_level.txt
jaraco_itertools-6.4.2.dist-info/RECORD
